MANIFEST.in
README.md
setup.py
paper_cup/__init__.py
paper_cup/client.py
paper_cup/paper_cup.py
paper_cup.egg-info/PKG-INFO
paper_cup.egg-info/SOURCES.txt
paper_cup.egg-info/dependency_links.txt
paper_cup.egg-info/not-zip-safe
paper_cup.egg-info/requires.txt
paper_cup.egg-info/top_level.txt
paper_cup/test/__init__.py
paper_cup/test/test_client.py
paper_cup/test/test_paper_cup.py